{"Id":"300","Title":"Boné Pressão Rural - Preto com Amarelo 4 x Trator Patrão","Description":"DESCRIÇÃO DO PRODUTO: Boné Pressão Rural confeccionado em tecido brin 100% Algodão, Trucker Americano com detalhe em bordado e Silk alto relevo na parte frontal, bordado e silk na traseira , aba com 6 costuras e regulador reforçado de plástico ajustável na parte traseira.","Link":"https://www.francaboots.com.br/300-bone-pressao-rural-preto-com-amarelo-4-x-trator-patrao","Image_link":"https://www.francaboots.com.br/205-large/bone-pressao-rural-preto-com-amarelo-4-x-trator-patrao.jpg","Additional_image_link":["https://www.francaboots.com.br/206-large/bone-pressao-rural-preto-com-amarelo-4-x-trator-patrao.jpg","https://www.francaboots.com.br/207-large/bone-pressao-rural-preto-com-amarelo-4-x-trator-patrao.jpg","https://www.francaboots.com.br/208-large/bone-pressao-rural-preto-com-amarelo-4-x-trator-patrao.jpg"],"Condition":"new","Product_type":"187 > ACESSÓRIOS","Google_product_category":"187","Quantity":null,"Availability":"in stock","Price":"109.90 BRL","Mpn":"300","Identifier_exists":"FALSE","Gender":"unisex","Age_group":"adult","Shipping":{"Country":"BR","Service":"Standard","Price":"0.00 BRL"},"Shipping_weight":"0.20 kg"}
